CHANGES.txt
README.rst
bootstrap.py
buildout.cfg
setup.py
collective/__init__.py
collective.salesforce.content.egg-info/PKG-INFO
collective.salesforce.content.egg-info/SOURCES.txt
collective.salesforce.content.egg-info/dependency_links.txt
collective.salesforce.content.egg-info/entry_points.txt
collective.salesforce.content.egg-info/namespace_packages.txt
collective.salesforce.content.egg-info/not-zip-safe
collective.salesforce.content.egg-info/requires.txt
collective.salesforce.content.egg-info/top_level.txt
collective/salesforce/__init__.py
collective/salesforce/content/__init__.py
collective/salesforce/content/behaviors.py
collective/salesforce/content/configure.zcml
collective/salesforce/content/controlpanel.py
collective/salesforce/content/converters.py
collective/salesforce/content/events.py
collective/salesforce/content/fields.py
collective/salesforce/content/interfaces.py
collective/salesforce/content/meta.zcml
collective/salesforce/content/schema.py
collective/salesforce/content/setuphandlers.py
collective/salesforce/content/subscribers.py
collective/salesforce/content/sync.py
collective/salesforce/content/upgrade.py
collective/salesforce/content/utils.py
collective/salesforce/content/vocabularies.py
collective/salesforce/content/profiles/default/browserlayer.xml
collective/salesforce/content/profiles/default/catalog.xml
collective/salesforce/content/profiles/default/collective-salesforce-content-various.txt
collective/salesforce/content/profiles/default/controlpanel.xml
collective/salesforce/content/profiles/default/metadata.xml
collective/salesforce/content/profiles/default/registry.xml
collective/salesforce/content/tests/__init__.py
collective/salesforce/content/tests/test_behaviors.py
collective/salesforce/content/tests/test_converters.py
collective/salesforce/content/tests/test_schema.py
collective/salesforce/content/tests/test_utils.py
docs/Makefile
docs/conf.py
docs/directives.rst
docs/gettingstarted.rst
docs/howto.rst
docs/index.rst