Metadata-Version: 1.0
Name: collective.salesforce.content
Version: 1.1
Summary: Behaviors for creating Dexterity content types that integrate with Salesforce.
Home-page: http://github.com/groundwire/collective.salesforce.content
Author: Matt Yoder, Groundwire
Author-email: mattyoder@groundwire.org
License: GPL
Keywords: Plone Dexterity Salesforce behavior integration
Platform: UNKNOWN
Classifier: Framework :: Plone
Classifier: Programming Language :: Python
